Metadata-Version: 2.1
Name: stacking-fmri
Version: 0.1.1
Summary: An implementation of stacked regression for functional MRI (fMRI) data
Home-page: https://github.com/brainML/Stacking
Download-URL: https://github.com/brainML/Stacking/archive/refs/heads/main.zip
Author: Ruogu Lin
Author-email: ruogulin@cs.cmu.edu
Keywords: stacking,brain,fmri
Platform: any
Classifier: Development Status :: 3 - Alpha
Classifier: Intended Audience :: Developers
Classifier: License :: OSI Approved :: MIT License
Classifier: Programming Language :: Python :: 3
License-File: LICENSE.txt
